{
  "timestamp": "2026-02-07T04:02:40.060316",
  "hostname": "hackathon0-1vcpu-1gb",
  "system": {
    "uptime": "20 days, 10:27:29.060360",
    "cpu_count": 1,
    "cpu_percent": 100.0
  },
  "memory": {
    "total_gb": 1.9218788146972656,
    "available_gb": 0.2963447570800781,
    "percent": 84.6,
    "used_gb": 1.6255340576171875
  },
  "disk": {
    "total_gb": 23.17425537109375,
    "used_gb": 17.72262191772461,
    "free_gb": 5.436008453369141,
    "percent": 76.5
  },
  "network": {
    "connections": 589,
    "interfaces": {
      "lo": {
        "bytes_sent": 17309041339,
        "bytes_recv": 17309041339,
        "packets_sent": 71033488,
        "packets_recv": 71033488
      },
      "eth0": {
        "bytes_sent": 9786138582,
        "bytes_recv": 26509620536,
        "packets_sent": 58209437,
        "packets_recv": 51755447
      },
      "eth1": {
        "bytes_sent": 4150228,
        "bytes_recv": 34586,
        "packets_sent": 98464,
        "packets_recv": 493
      },
      "docker0": {
        "bytes_sent": 0,
        "bytes_recv": 0,
        "packets_sent": 0,
        "packets_recv": 0
      },
      "br-f94ce15414f1": {
        "bytes_sent": 2677703,
        "bytes_recv": 2021428,
        "packets_sent": 20918,
        "packets_recv": 15636
      },
      "br-774ef7eb3543": {
        "bytes_sent": 8253419236,
        "bytes_recv": 6787075607,
        "packets_sent": 30829815,
        "packets_recv": 22335940
      },
      "veth4f47366": {
        "bytes_sent": 12157033930,
        "bytes_recv": 12453317297,
        "packets_sent": 56732864,
        "packets_recv": 54543169
      },
      "veth10648ad": {
        "bytes_sent": 20706752801,
        "bytes_recv": 19256795079,
        "packets_sent": 85373216,
        "packets_recv": 79068553
      }
    }
  },
  "processes": {
    "gmail-watcher": {
      "status": "online",
      "cpu": 0,
      "memory_mb": 0.0,
      "uptime": 1769596136570,
      "restarts": 0,
      "pid": 2394377
    },
    "calendar-watcher": {
      "status": "stopped",
      "cpu": 0,
      "memory_mb": 0.0,
      "uptime": 1769591310657,
      "restarts": 0,
      "pid": 0
    },
    "odoo-watcher": {
      "status": "online",
      "cpu": 0,
      "memory_mb": 0.0,
      "uptime": 1769610995942,
      "restarts": 2,
      "pid": 2413366
    },
    "cloud-health-monitor": {
      "status": "online",
      "cpu": 0,
      "memory_mb": 8.0,
      "uptime": 1768893756727,
      "restarts": 0,
      "pid": 406903
    },
    "auto-approver": {
      "status": "online",
      "cpu": 0,
      "memory_mb": 0.0,
      "uptime": 1768858015732,
      "restarts": 0,
      "pid": 317853
    },
    "slack-watcher": {
      "status": "online",
      "cpu": 0,
      "memory_mb": 0.0,
      "uptime": 1769596260697,
      "restarts": 1,
      "pid": 2394791
    },
    "git-sync-push": {
      "status": "online",
      "cpu": 0,
      "memory_mb": 8.0,
      "uptime": 1770059503670,
      "restarts": 0,
      "pid": 1025132
    }
  },
  "alerts": [
    "HIGH CPU: 100.0%",
    "HIGH MEMORY: 84.6%",
    "PROCESS STOPPED: calendar-watcher"
  ]
}