{
  "timestamp": "2026-01-25T20:41:01.118535",
  "hostname": "hackathon0-1vcpu-1gb",
  "system": {
    "uptime": "8 days, 3:05:50.118575",
    "cpu_count": 1,
    "cpu_percent": 100.0
  },
  "memory": {
    "total_gb": 1.9218788146972656,
    "available_gb": 0.3093681335449219,
    "percent": 83.9,
    "used_gb": 1.6125106811523438
  },
  "disk": {
    "total_gb": 23.17425537109375,
    "used_gb": 6.637168884277344,
    "free_gb": 16.521461486816406,
    "percent": 28.7
  },
  "network": {
    "connections": 9,
    "interfaces": {
      "lo": {
        "bytes_sent": 36953745,
        "bytes_recv": 36953745,
        "packets_sent": 373328,
        "packets_recv": 373328
      },
      "eth0": {
        "bytes_sent": 636138350,
        "bytes_recv": 1368660865,
        "packets_sent": 3060554,
        "packets_recv": 3243811
      },
      "eth1": {
        "bytes_sent": 870392,
        "bytes_recv": 14286,
        "packets_sent": 20582,
        "packets_recv": 203
      }
    }
  },
  "processes": {
    "gmail-watcher": {
      "status": "online",
      "cpu": 0,
      "memory_mb": 24.58984375,
      "uptime": 1769373662779,
      "restarts": 228524,
      "pid": 1770846
    },
    "calendar-watcher": {
      "status": "online",
      "cpu": 0,
      "memory_mb": 21.375,
      "uptime": 1769373663097,
      "restarts": 228513,
      "pid": 1770847
    },
    "slack-watcher": {
      "status": "online",
      "cpu": 0,
      "memory_mb": 15.453125,
      "uptime": 1769373663317,
      "restarts": 615641,
      "pid": 1770848
    },
    "odoo-watcher": {
      "status": "online",
      "cpu": 0,
      "memory_mb": 20.625,
      "uptime": 1768855224700,
      "restarts": 1,
      "pid": 305632
    },
    "git-sync-push": {
      "status": "stopped",
      "cpu": 0,
      "memory_mb": 0.0,
      "uptime": 1769373600003,
      "restarts": 0,
      "pid": 0
    },
    "cloud-health-monitor": {
      "status": "online",
      "cpu": 0.1,
      "memory_mb": 15.875,
      "uptime": 1768893756727,
      "restarts": 30,
      "pid": 406903
    },
    "auto-approver": {
      "status": "online",
      "cpu": 0,
      "memory_mb": 28.2265625,
      "uptime": 1768858015732,
      "restarts": 10,
      "pid": 317853
    }
  },
  "alerts": [
    "HIGH CPU: 100.0%",
    "HIGH MEMORY: 83.9%",
    "PROCESS STOPPED: git-sync-push"
  ]
}