{
  "timestamp": "2026-02-04T00:36:04.203697",
  "hostname": "hackathon0-1vcpu-1gb",
  "system": {
    "uptime": "17 days, 7:00:53.203737",
    "cpu_count": 1,
    "cpu_percent": 100.0
  },
  "memory": {
    "total_gb": 1.9218788146972656,
    "available_gb": 0.3100738525390625,
    "percent": 83.9,
    "used_gb": 1.6118049621582031
  },
  "disk": {
    "total_gb": 23.17425537109375,
    "used_gb": 15.720935821533203,
    "free_gb": 7.437694549560547,
    "percent": 67.9
  },
  "network": {
    "connections": 695,
    "interfaces": {
      "lo": {
        "bytes_sent": 11672111251,
        "bytes_recv": 11672111251,
        "packets_sent": 48056165,
        "packets_recv": 48056165
      },
      "eth0": {
        "bytes_sent": 6711087336,
        "bytes_recv": 18544098295,
        "packets_sent": 39774163,
        "packets_recv": 35488520
      },
      "eth1": {
        "bytes_sent": 3467784,
        "bytes_recv": 29406,
        "packets_sent": 82272,
        "packets_recv": 419
      },
      "docker0": {
        "bytes_sent": 0,
        "bytes_recv": 0,
        "packets_sent": 0,
        "packets_recv": 0
      },
      "br-f94ce15414f1": {
        "bytes_sent": 2677703,
        "bytes_recv": 2021428,
        "packets_sent": 20918,
        "packets_recv": 15636
      },
      "br-774ef7eb3543": {
        "bytes_sent": 5556472388,
        "bytes_recv": 4561192211,
        "packets_sent": 20753752,
        "packets_recv": 15034475
      },
      "veth4f47366": {
        "bytes_sent": 8225519709,
        "bytes_recv": 8416332367,
        "packets_sent": 38252003,
        "packets_recv": 36778462
      },
      "veth10648ad": {
        "bytes_sent": 13972815913,
        "bytes_recv": 12997182062,
        "packets_sent": 57532373,
        "packets_recv": 53286300
      }
    }
  },
  "processes": {
    "gmail-watcher": {
      "status": "online",
      "cpu": 0,
      "memory_mb": 0.0,
      "uptime": 1769596136570,
      "restarts": 0,
      "pid": 2394377
    },
    "calendar-watcher": {
      "status": "stopped",
      "cpu": 0,
      "memory_mb": 0.0,
      "uptime": 1769591310657,
      "restarts": 0,
      "pid": 0
    },
    "odoo-watcher": {
      "status": "online",
      "cpu": 0,
      "memory_mb": 0.0,
      "uptime": 1769610995942,
      "restarts": 2,
      "pid": 2413366
    },
    "cloud-health-monitor": {
      "status": "online",
      "cpu": 0,
      "memory_mb": 9.875,
      "uptime": 1768893756727,
      "restarts": 0,
      "pid": 406903
    },
    "auto-approver": {
      "status": "online",
      "cpu": 0,
      "memory_mb": 0.0,
      "uptime": 1768858015732,
      "restarts": 0,
      "pid": 317853
    },
    "slack-watcher": {
      "status": "online",
      "cpu": 0,
      "memory_mb": 0.0,
      "uptime": 1769596260697,
      "restarts": 1,
      "pid": 2394791
    },
    "git-sync-push": {
      "status": "online",
      "cpu": 0,
      "memory_mb": 9.875,
      "uptime": 1770059503670,
      "restarts": 0,
      "pid": 1025132
    }
  },
  "alerts": [
    "HIGH CPU: 100.0%",
    "HIGH MEMORY: 83.9%",
    "PROCESS STOPPED: calendar-watcher"
  ]
}