{
  "timestamp": "2026-02-09T23:57:26.590498",
  "hostname": "hackathon0-1vcpu-1gb",
  "system": {
    "uptime": "23 days, 6:22:15.590532",
    "cpu_count": 1,
    "cpu_percent": 100.0
  },
  "memory": {
    "total_gb": 1.9218788146972656,
    "available_gb": 0.297637939453125,
    "percent": 84.5,
    "used_gb": 1.6242408752441406
  },
  "disk": {
    "total_gb": 23.17425537109375,
    "used_gb": 19.528411865234375,
    "free_gb": 3.630218505859375,
    "percent": 84.3
  },
  "network": {
    "connections": 613,
    "interfaces": {
      "lo": {
        "bytes_sent": 22007275406,
        "bytes_recv": 22007275406,
        "packets_sent": 90211009,
        "packets_recv": 90211009
      },
      "eth0": {
        "bytes_sent": 12469934263,
        "bytes_recv": 33396740731,
        "packets_sent": 74254565,
        "packets_recv": 65889293
      },
      "eth1": {
        "bytes_sent": 4154988,
        "bytes_recv": 39206,
        "packets_sent": 98532,
        "packets_recv": 559
      },
      "docker0": {
        "bytes_sent": 0,
        "bytes_recv": 0,
        "packets_sent": 0,
        "packets_recv": 0
      },
      "br-f94ce15414f1": {
        "bytes_sent": 2677703,
        "bytes_recv": 2021428,
        "packets_sent": 20918,
        "packets_recv": 15636
      },
      "br-774ef7eb3543": {
        "bytes_sent": 10499568807,
        "bytes_recv": 8640903780,
        "packets_sent": 39219791,
        "packets_recv": 28415101
      },
      "veth4f47366": {
        "bytes_sent": 15432696579,
        "bytes_recv": 15816906998,
        "packets_sent": 72132343,
        "packets_recv": 69344121
      },
      "veth10648ad": {
        "bytes_sent": 26316496763,
        "bytes_recv": 24471389465,
        "packets_sent": 108564211,
        "packets_recv": 100547126
      }
    }
  },
  "processes": {
    "gmail-watcher": {
      "status": "online",
      "cpu": 0,
      "memory_mb": 0.0,
      "uptime": 1769596136570,
      "restarts": 0,
      "pid": 2394377
    },
    "calendar-watcher": {
      "status": "stopped",
      "cpu": 0,
      "memory_mb": 0.0,
      "uptime": 1769591310657,
      "restarts": 0,
      "pid": 0
    },
    "odoo-watcher": {
      "status": "online",
      "cpu": 0,
      "memory_mb": 0.0,
      "uptime": 1769610995942,
      "restarts": 2,
      "pid": 2413366
    },
    "cloud-health-monitor": {
      "status": "online",
      "cpu": 0,
      "memory_mb": 8.0,
      "uptime": 1768893756727,
      "restarts": 0,
      "pid": 406903
    },
    "auto-approver": {
      "status": "online",
      "cpu": 0,
      "memory_mb": 0.0,
      "uptime": 1768858015732,
      "restarts": 0,
      "pid": 317853
    },
    "slack-watcher": {
      "status": "online",
      "cpu": 0,
      "memory_mb": 0.0,
      "uptime": 1769596260697,
      "restarts": 1,
      "pid": 2394791
    },
    "git-sync-push": {
      "status": "online",
      "cpu": 0,
      "memory_mb": 8.0,
      "uptime": 1770059503670,
      "restarts": 0,
      "pid": 1025132
    }
  },
  "alerts": [
    "HIGH CPU: 100.0%",
    "HIGH MEMORY: 84.5%",
    "HIGH DISK: 84.3%",
    "PROCESS STOPPED: calendar-watcher"
  ]
}