{
  "timestamp": "2026-01-23T17:06:15.650993",
  "hostname": "hackathon0-1vcpu-1gb",
  "system": {
    "uptime": "5 days, 23:31:04.651023",
    "cpu_count": 1,
    "cpu_percent": 100.0
  },
  "memory": {
    "total_gb": 1.9218788146972656,
    "available_gb": 0.3202552795410156,
    "percent": 83.3,
    "used_gb": 1.60162353515625
  },
  "disk": {
    "total_gb": 23.17425537109375,
    "used_gb": 5.932151794433594,
    "free_gb": 17.226478576660156,
    "percent": 25.6
  },
  "network": {
    "connections": 9,
    "interfaces": {
      "lo": {
        "bytes_sent": 28879433,
        "bytes_recv": 28879433,
        "packets_sent": 291494,
        "packets_recv": 291494
      },
      "eth0": {
        "bytes_sent": 443312731,
        "bytes_recv": 1087968076,
        "packets_sent": 2024007,
        "packets_recv": 2139004
      },
      "eth1": {
        "bytes_sent": 866752,
        "bytes_recv": 10786,
        "packets_sent": 20530,
        "packets_recv": 153
      }
    }
  },
  "processes": {
    "gmail-watcher": {
      "status": "online",
      "cpu": 0,
      "memory_mb": 11.5,
      "uptime": 1769187977849,
      "restarts": 147317,
      "pid": 1208858
    },
    "calendar-watcher": {
      "status": "online",
      "cpu": 0,
      "memory_mb": 11.0,
      "uptime": 1769187977881,
      "restarts": 147312,
      "pid": 1208859
    },
    "slack-watcher": {
      "status": "online",
      "cpu": 0,
      "memory_mb": 20.703125,
      "uptime": 1769187977412,
      "restarts": 398032,
      "pid": 1208857
    },
    "odoo-watcher": {
      "status": "online",
      "cpu": 0,
      "memory_mb": 21.0,
      "uptime": 1768855224700,
      "restarts": 1,
      "pid": 305632
    },
    "git-sync-push": {
      "status": "stopped",
      "cpu": 0,
      "memory_mb": 0.0,
      "uptime": 1769187900005,
      "restarts": 0,
      "pid": 0
    },
    "cloud-health-monitor": {
      "status": "online",
      "cpu": 0.2,
      "memory_mb": 16.0,
      "uptime": 1768893756727,
      "restarts": 30,
      "pid": 406903
    },
    "auto-approver": {
      "status": "online",
      "cpu": 0,
      "memory_mb": 28.6015625,
      "uptime": 1768858015732,
      "restarts": 10,
      "pid": 317853
    }
  },
  "alerts": [
    "HIGH CPU: 100.0%",
    "HIGH MEMORY: 83.3%",
    "PROCESS STOPPED: git-sync-push"
  ]
}