{
  "timestamp": "2026-02-13T18:20:30.086012",
  "hostname": "hackathon0-1vcpu-1gb",
  "system": {
    "uptime": "27 days, 0:45:19.086046",
    "cpu_count": 1,
    "cpu_percent": 100.0
  },
  "memory": {
    "total_gb": 1.9218788146972656,
    "available_gb": 0.3068199157714844,
    "percent": 84.0,
    "used_gb": 1.6150588989257812
  },
  "disk": {
    "total_gb": 23.17425537109375,
    "used_gb": 21.53818130493164,
    "free_gb": 1.6204490661621094,
    "percent": 93.0
  },
  "network": {
    "connections": 589,
    "interfaces": {
      "lo": {
        "bytes_sent": 27985231729,
        "bytes_recv": 27985231729,
        "packets_sent": 114644396,
        "packets_recv": 114644396
      },
      "eth0": {
        "bytes_sent": 15900192046,
        "bytes_recv": 42162464838,
        "packets_sent": 94749937,
        "packets_recv": 83904989
      },
      "eth1": {
        "bytes_sent": 4161358,
        "bytes_recv": 45436,
        "packets_sent": 98623,
        "packets_recv": 648
      },
      "docker0": {
        "bytes_sent": 0,
        "bytes_recv": 0,
        "packets_sent": 0,
        "packets_recv": 0
      },
      "br-f94ce15414f1": {
        "bytes_sent": 2677703,
        "bytes_recv": 2021428,
        "packets_sent": 20918,
        "packets_recv": 15636
      },
      "br-774ef7eb3543": {
        "bytes_sent": 13355512533,
        "bytes_recv": 10997948064,
        "packets_sent": 49889376,
        "packets_recv": 36146861
      },
      "veth4f47366": {
        "bytes_sent": 19598223945,
        "bytes_recv": 20094141035,
        "packets_sent": 91716395,
        "packets_recv": 88165865
      },
      "veth10648ad": {
        "bytes_sent": 33449680756,
        "bytes_recv": 31102199595,
        "packets_sent": 138055629,
        "packets_recv": 127862850
      }
    }
  },
  "processes": {
    "gmail-watcher": {
      "status": "online",
      "cpu": 0,
      "memory_mb": 0.0,
      "uptime": 1769596136570,
      "restarts": 0,
      "pid": 2394377
    },
    "calendar-watcher": {
      "status": "stopped",
      "cpu": 0,
      "memory_mb": 0.0,
      "uptime": 1769591310657,
      "restarts": 0,
      "pid": 0
    },
    "odoo-watcher": {
      "status": "online",
      "cpu": 0,
      "memory_mb": 0.0,
      "uptime": 1769610995942,
      "restarts": 2,
      "pid": 2413366
    },
    "cloud-health-monitor": {
      "status": "online",
      "cpu": 0,
      "memory_mb": 8.375,
      "uptime": 1768893756727,
      "restarts": 0,
      "pid": 406903
    },
    "auto-approver": {
      "status": "online",
      "cpu": 0,
      "memory_mb": 0.0,
      "uptime": 1768858015732,
      "restarts": 0,
      "pid": 317853
    },
    "slack-watcher": {
      "status": "online",
      "cpu": 0,
      "memory_mb": 0.0,
      "uptime": 1769596260697,
      "restarts": 1,
      "pid": 2394791
    },
    "git-sync-push": {
      "status": "online",
      "cpu": 0,
      "memory_mb": 8.375,
      "uptime": 1770059503670,
      "restarts": 0,
      "pid": 1025132
    }
  },
  "alerts": [
    "HIGH CPU: 100.0%",
    "HIGH MEMORY: 84.0%",
    "HIGH DISK: 93.0%",
    "PROCESS STOPPED: calendar-watcher"
  ]
}