{
  "timestamp": "2026-02-14T19:44:06.821352",
  "hostname": "hackathon0-1vcpu-1gb",
  "system": {
    "uptime": "28 days, 2:08:55.821399",
    "cpu_count": 1,
    "cpu_percent": 100.0
  },
  "memory": {
    "total_gb": 1.9218788146972656,
    "available_gb": 0.30738067626953125,
    "percent": 84.0,
    "used_gb": 1.6144981384277344
  },
  "disk": {
    "total_gb": 23.17425537109375,
    "used_gb": 22.1265869140625,
    "free_gb": 1.03204345703125,
    "percent": 95.5
  },
  "network": {
    "connections": 676,
    "interfaces": {
      "lo": {
        "bytes_sent": 29831365448,
        "bytes_recv": 29831365448,
        "packets_sent": 121858023,
        "packets_recv": 121858023
      },
      "eth0": {
        "bytes_sent": 16653685086,
        "bytes_recv": 44010367068,
        "packets_sent": 98922905,
        "packets_recv": 87698362
      },
      "eth1": {
        "bytes_sent": 4163108,
        "bytes_recv": 47186,
        "packets_sent": 98648,
        "packets_recv": 673
      },
      "docker0": {
        "bytes_sent": 0,
        "bytes_recv": 0,
        "packets_sent": 0,
        "packets_recv": 0
      },
      "br-f94ce15414f1": {
        "bytes_sent": 2677703,
        "bytes_recv": 2021428,
        "packets_sent": 20918,
        "packets_recv": 15636
      },
      "br-774ef7eb3543": {
        "bytes_sent": 14263093747,
        "bytes_recv": 11746966221,
        "packets_sent": 53280762,
        "packets_recv": 38604653
      },
      "veth4f47366": {
        "bytes_sent": 20921159789,
        "bytes_recv": 21452664440,
        "packets_sent": 97935172,
        "packets_recv": 94143640
      },
      "veth10648ad": {
        "bytes_sent": 35715787055,
        "bytes_recv": 33208561004,
        "packets_sent": 147424814,
        "packets_recv": 136539395
      }
    }
  },
  "processes": {
    "gmail-watcher": {
      "status": "online",
      "cpu": 0,
      "memory_mb": 0.0,
      "uptime": 1769596136570,
      "restarts": 0,
      "pid": 2394377
    },
    "calendar-watcher": {
      "status": "stopped",
      "cpu": 0,
      "memory_mb": 0.0,
      "uptime": 1769591310657,
      "restarts": 0,
      "pid": 0
    },
    "odoo-watcher": {
      "status": "online",
      "cpu": 0,
      "memory_mb": 0.0,
      "uptime": 1769610995942,
      "restarts": 2,
      "pid": 2413366
    },
    "cloud-health-monitor": {
      "status": "online",
      "cpu": 0,
      "memory_mb": 8.375,
      "uptime": 1768893756727,
      "restarts": 0,
      "pid": 406903
    },
    "auto-approver": {
      "status": "online",
      "cpu": 0,
      "memory_mb": 0.0,
      "uptime": 1768858015732,
      "restarts": 0,
      "pid": 317853
    },
    "slack-watcher": {
      "status": "online",
      "cpu": 0,
      "memory_mb": 0.0,
      "uptime": 1769596260697,
      "restarts": 1,
      "pid": 2394791
    },
    "git-sync-push": {
      "status": "online",
      "cpu": 0,
      "memory_mb": 8.375,
      "uptime": 1770059503670,
      "restarts": 0,
      "pid": 1025132
    }
  },
  "alerts": [
    "HIGH CPU: 100.0%",
    "HIGH MEMORY: 84.0%",
    "HIGH DISK: 95.5%",
    "PROCESS STOPPED: calendar-watcher"
  ]
}