{
  "timestamp": "2026-02-05T21:57:01.638753",
  "hostname": "hackathon0-1vcpu-1gb",
  "system": {
    "uptime": "19 days, 4:21:50.638790",
    "cpu_count": 1,
    "cpu_percent": 100.0
  },
  "memory": {
    "total_gb": 1.9218788146972656,
    "available_gb": 0.3130149841308594,
    "percent": 83.7,
    "used_gb": 1.6088638305664062
  },
  "disk": {
    "total_gb": 23.17425537109375,
    "used_gb": 17.08993148803711,
    "free_gb": 6.068698883056641,
    "percent": 73.8
  },
  "network": {
    "connections": 704,
    "interfaces": {
      "lo": {
        "bytes_sent": 15097685763,
        "bytes_recv": 15097685763,
        "packets_sent": 62084723,
        "packets_recv": 62084723
      },
      "eth0": {
        "bytes_sent": 8587207200,
        "bytes_recv": 23476199503,
        "packets_sent": 51048192,
        "packets_recv": 45448981
      },
      "eth1": {
        "bytes_sent": 4148128,
        "bytes_recv": 32556,
        "packets_sent": 98434,
        "packets_recv": 464
      },
      "docker0": {
        "bytes_sent": 0,
        "bytes_recv": 0,
        "packets_sent": 0,
        "packets_recv": 0
      },
      "br-f94ce15414f1": {
        "bytes_sent": 2677703,
        "bytes_recv": 2021428,
        "packets_sent": 20918,
        "packets_recv": 15636
      },
      "br-774ef7eb3543": {
        "bytes_sent": 7190448646,
        "bytes_recv": 5909736029,
        "packets_sent": 26858786,
        "packets_recv": 19458483
      },
      "veth4f47366": {
        "bytes_sent": 10607440318,
        "bytes_recv": 10862107311,
        "packets_sent": 49448419,
        "packets_recv": 47541172
      },
      "veth10648ad": {
        "bytes_sent": 18052570195,
        "bytes_recv": 16789579521,
        "packets_sent": 74400161,
        "packets_recv": 68906680
      }
    }
  },
  "processes": {
    "gmail-watcher": {
      "status": "online",
      "cpu": 0,
      "memory_mb": 0.0,
      "uptime": 1769596136570,
      "restarts": 0,
      "pid": 2394377
    },
    "calendar-watcher": {
      "status": "stopped",
      "cpu": 0,
      "memory_mb": 0.0,
      "uptime": 1769591310657,
      "restarts": 0,
      "pid": 0
    },
    "odoo-watcher": {
      "status": "online",
      "cpu": 0,
      "memory_mb": 0.0,
      "uptime": 1769610995942,
      "restarts": 2,
      "pid": 2413366
    },
    "cloud-health-monitor": {
      "status": "online",
      "cpu": 0,
      "memory_mb": 8.25,
      "uptime": 1768893756727,
      "restarts": 0,
      "pid": 406903
    },
    "auto-approver": {
      "status": "online",
      "cpu": 0,
      "memory_mb": 0.0,
      "uptime": 1768858015732,
      "restarts": 0,
      "pid": 317853
    },
    "slack-watcher": {
      "status": "online",
      "cpu": 0,
      "memory_mb": 0.0,
      "uptime": 1769596260697,
      "restarts": 1,
      "pid": 2394791
    },
    "git-sync-push": {
      "status": "online",
      "cpu": 0,
      "memory_mb": 8.25,
      "uptime": 1770059503670,
      "restarts": 0,
      "pid": 1025132
    }
  },
  "alerts": [
    "HIGH CPU: 100.0%",
    "HIGH MEMORY: 83.7%",
    "PROCESS STOPPED: calendar-watcher"
  ]
}